setup.py
palindd/__init__.py
palindd/palin.py
palindd.egg-info/PKG-INFO
palindd.egg-info/SOURCES.txt
palindd.egg-info/dependency_links.txt
palindd.egg-info/top_level.txt