Metadata-Version: 1.1
Name: palindd
Version: 0.1
Summary: check if a string is palindrome or not!
Home-page: https://github.com/khanstark/palindrome
Author: Kaif Khan
Author-email: kaifkhan.khan0@gmail.com
License: MIT
Keywords: palindrome
Platform: UNKNOWN
Classifier: Development Status :: 3 - Alpha
Classifier: Intended Audience :: Developers
Classifier: Topic :: Software Development :: Build Tools
Classifier: License :: OSI Approved :: MIT License
Classifier: Programming Language :: Python :: 3
Classifier: Programming Language :: Python :: 2
Classifier: Programming Language :: Python :: 3.5
Classifier: Programming Language :: Python :: 3.6
